ForensicHub/__init__.py
ForensicHub/cli.py
ForensicHub/registry.py
ForensicHub/version.py
ForensicHub/cli_funcs/__init__.py
ForensicHub/cli_funcs/cli_data.py
ForensicHub/cli_funcs/cli_guide.py
ForensicHub/cli_funcs/cli_init.py
ForensicHub/cli_funcs/copy.py
ForensicHub/common/__init__.py
ForensicHub/common/backbones/__init__.py
ForensicHub/common/backbones/resnet.py
ForensicHub/common/evaluation/AUC.py
ForensicHub/common/evaluation/Accuracy.py
ForensicHub/common/evaluation/F1.py
ForensicHub/common/evaluation/IOU.py
ForensicHub/common/evaluation/__init__.py
ForensicHub/common/evaluation/abstract_class.py
ForensicHub/common/evaluation/metrics.py
ForensicHub/common/evaluation/temp.py
ForensicHub/common/utils/__init__.py
ForensicHub/common/utils/config.py
ForensicHub/common/utils/dataset.py
ForensicHub/common/utils/paths.py
ForensicHub/common/utils/yaml.py
ForensicHub/core/__init__.py
ForensicHub/core/base_dataset.py
ForensicHub/core/base_model.py
ForensicHub/core/base_transform.py
ForensicHub/tasks/__init__.py
ForensicHub/tasks/aigc/__init__.py
ForensicHub/tasks/aigc/datasets/__init__.py
ForensicHub/tasks/aigc/datasets/label_dataset.py
ForensicHub/tasks/aigc/models/__init__.py
ForensicHub/tasks/aigc/models/dire/__init__.py
ForensicHub/tasks/aigc/transforms/__init__.py
ForensicHub/tasks/aigc/transforms/aigc_transforms.py
ForensicHub/tasks/deepfake/__init__.py
ForensicHub/tasks/deepfake/datasets/__init__.py
ForensicHub/tasks/deepfake/models/__init__.py
ForensicHub/tasks/deepfake/transforms/__init__.py
ForensicHub/tasks/document/__init__.py
ForensicHub/tasks/document/datasets/__init__.py
ForensicHub/tasks/document/models/__init__.py
ForensicHub/tasks/document/transforms/__init__.py
ForensicHub/tasks/imdl/__init__.py
ForensicHub/tasks/imdl/datasets/__init__.py
ForensicHub/tasks/imdl/datasets/abstract_dataset.py
ForensicHub/tasks/imdl/datasets/balanced_dataset.py
ForensicHub/tasks/imdl/datasets/iml_datasets.py
ForensicHub/tasks/imdl/datasets/utils.py
forensichub-0.0.1.dist-info/METADATA
forensichub-0.0.1.dist-info/WHEEL
forensichub-0.0.1.dist-info/entry_points.txt
forensichub-0.0.1.dist-info/top_level.txt
forensichub-0.0.1.dist-info/RECORD
